{
    "word_family": [
        "gathering",
        "gatherer",
        "ingathering"
    ],
    "entries": [
        {
            "pos": "verb",
            "senses": [
                {
                    "sense_id": "3275e904-7a99-3b35-a11d-250ce05f8480",
                    "sense_definition": "simple past and past participle of <w>gather</w>",
                    "learner_level": "A2",
                    "frequency": "High",
                    "semantic_group_id": "",
                    "name_type": "no",
                    "examples": [
                        {
                            "text": "The whole family <w>gathered</w> together for the holiday dinner.",
                            "target_lang_translations": {
                                "ru": "Вся семья <w>собралась</w> вместе на праздничный ужин."
                            }
                        },
                        {
                            "text": "Dark clouds <w>gathered</w> in the sky before the storm started.",
                            "target_lang_translations": {
                                "ru": "Темные тучи <w>сгустились</w> на небе перед началом грозы."
                            }
                        }
                    ],
                    "synonyms": [
                        "collected",
                        "assembled",
                        "accumulated"
                    ],
                    "antonyms": [
                        "scattered",
                        "dispersed"
                    ],
                    "common_phrases": [
                        "gathered together",
                        "gathered around",
                        "gathered up",
                        "gathered dust"
                    ],
                    "target_lang_definitions": {
                        "ru": "Прошедшее время и причастие прошедшего времени от глагола gather (собирать, собираться)"
                    },
                    "translations": {
                        "ru": [
                            {
                                "target_lang_word": "собрался",
                                "target_lang_sense_clarification": "о людях или группах (встретиться вместе)"
                            },
                            {
                                "target_lang_word": "сгустился",
                                "target_lang_sense_clarification": "о тучах, темноте или атмосфере"
                            },
                            {
                                "target_lang_word": "собрал",
                                "target_lang_sense_clarification": "о предметах, информации или урожае"
                            }
                        ]
                    }
                }
            ]
        },
        {
            "pos": "adjective",
            "senses": [
                {
                    "sense_id": "6e088008-6ac6-323e-8eab-b4a3a745d30f",
                    "sense_definition": "focused, centered, or achieving a state of shared spiritual unity",
                    "learner_level": "C2",
                    "frequency": "Low",
                    "semantic_group_id": "",
                    "name_type": "no",
                    "examples": [
                        {
                            "text": "She felt calm and <w>gathered</w> before giving her speech.",
                            "target_lang_translations": {
                                "ru": "Она чувствовала себя спокойной и <w>собранной</w> перед выступлением."
                            }
                        },
                        {
                            "text": "The group sat in a <w>gathered</w> silence, feeling deeply connected.",
                            "target_lang_translations": {
                                "ru": "Группа сидела в <w>сосредоточенном</w> молчании, чувствуя глубокую связь."
                            }
                        }
                    ],
                    "synonyms": [
                        "focused",
                        "centered",
                        "composed"
                    ],
                    "antonyms": [
                        "distracted",
                        "scattered"
                    ],
                    "common_phrases": [
                        "gathered meeting",
                        "gathered silence"
                    ],
                    "target_lang_definitions": {
                        "ru": "Сосредоточенный, сфокусированный или достигший состояния духовного единства"
                    },
                    "translations": {
                        "ru": [
                            {
                                "target_lang_word": "собранный",
                                "target_lang_sense_clarification": "сфокусированный, организованный (о человеке)"
                            },
                            {
                                "target_lang_word": "сосредоточенный",
                                "target_lang_sense_clarification": "о внимании или тишине"
                            }
                        ]
                    }
                }
            ]
        }
    ]
}