{
    "word_family": [
        "humectant",
        "humectation"
    ],
    "entries": [
        {
            "pos": "verb",
            "senses": [
                {
                    "sense_id": "e1227539-5e57-3030-9ce8-5896d449823b",
                    "sense_definition": "To moisten or make something slightly wet.",
                    "learner_level": "C2",
                    "frequency": "VeryLow",
                    "semantic_group_id": "",
                    "name_type": "no",
                    "examples": [
                        {
                            "text": "The scientist used a special solution to <w>humectate</w> the biological sample before examining it.",
                            "target_lang_translations": {
                                "ru": "Ученый использовал специальный раствор, чтобы <w>увлажнить</w> биологический образец перед его изучением."
                            }
                        },
                        {
                            "text": "You can use this spray to <w>humectate</w> the air in the room and make breathing easier.",
                            "target_lang_translations": {
                                "ru": "Вы можете использовать этот спрей, чтобы <w>увлажнить</w> воздух в комнате и облегчить дыхание."
                            }
                        }
                    ],
                    "synonyms": [
                        "moisten",
                        "dampen",
                        "wet",
                        "hydrate"
                    ],
                    "antonyms": [
                        "dry",
                        "desiccate",
                        "dehydrate"
                    ],
                    "common_phrases": [
                        "humectate the skin",
                        "humectate the air"
                    ],
                    "target_lang_definitions": {
                        "ru": "Увлажнять или делать что-либо слегка влажным."
                    },
                    "translations": {
                        "ru": [
                            {
                                "target_lang_word": "увлажнять",
                                "target_lang_sense_clarification": "насыщать влагой"
                            },
                            {
                                "target_lang_word": "смачивать",
                                "target_lang_sense_clarification": "делать мокрым поверхность"
                            }
                        ]
                    }
                }
            ]
        }
    ]
}