{
    "word_family": [
        "town",
        "townsfolk",
        "townsman",
        "townswoman",
        "township"
    ],
    "entries": [
        {
            "pos": "noun",
            "senses": [
                {
                    "sense_id": "b679ee0b-8bd1-3c44-8ff6-227ec0162ec9",
                    "sense_definition": "A person who lives in a town.",
                    "learner_level": "B2",
                    "frequency": "Low",
                    "semantic_group_id": "",
                    "name_type": "no",
                    "examples": [
                        {
                            "text": "Every <w>townsperson</w> was invited to the annual celebration in the main square."
                        },
                        {
                            "text": "An average <w>townsperson</w> might not know the full history of the ancient bridge."
                        }
                    ],
                    "synonyms": [
                        "town dweller",
                        "resident"
                    ],
                    "antonyms": [
                        "villager"
                    ],
                    "common_phrases": [
                        "local townsperson",
                        "average townsperson"
                    ]
                }
            ]
        }
    ]
}