{
    "word_family": [],
    "entries": [
        {
            "pos": "name",
            "senses": [
                {
                    "sense_id": "7712411a-b16b-3511-82d0-a8fac37e49b8",
                    "sense_definition": "Een jongensnaam.",
                    "learner_level": "A2",
                    "frequency": "High",
                    "semantic_group_id": "",
                    "name_type": "person_name",
                    "examples": [
                        {
                            "text": "Mijn buurman heet <w>Jeroen</w> en hij is erg aardig."
                        },
                        {
                            "text": "Ik ga vanavond met <w>Jeroen</w> naar de bioscoop."
                        }
                    ]
                }
            ]
        }
    ]
}