{
    "word": "aws",
    "lang_code": "en",
    "source_file_to_entries": {
        "raw-wiktextract-data.jsonl": [
            {
                "entry_id": "e4e347a9-a024-3e91-9ba3-33376803e83d",
                "word": "AWS",
                "pos": "name",
                "lang_code": "en",
                "forms": [],
                "senses": [
                    {
                        "sense_id": "d73c6e0f-3158-3489-ad11-39ddd3a46a97",
                        "entry_id": "e4e347a9-a024-3e91-9ba3-33376803e83d",
                        "glosses": [
                            "Initialism of Automatic Warning System."
                        ],
                        "tags": [
                            "abbreviation",
                            "alt-of",
                            "initialism"
                        ],
                        "examples": [
                            {
                                "example_id": "6d6450c4-bee9-4853-b92c-d59af3a8b458",
                                "sense_id": "d73c6e0f-3158-3489-ad11-39ddd3a46a97",
                                "text": "Furthermore, the train was equipped with AWS (Automatic Warning System), which would have provided an audible warning that a signal was being approached."
                            }
                        ]
                    },
                    {
                        "sense_id": "40a469c9-f541-3554-8119-608ebcf8558e",
                        "entry_id": "e4e347a9-a024-3e91-9ba3-33376803e83d",
                        "glosses": [
                            "Initialism of Amazon Web Services."
                        ],
                        "tags": [
                            "Internet",
                            "abbreviation",
                            "alt-of",
                            "initialism"
                        ],
                        "examples": [
                            {
                                "example_id": "09536815-16ad-478e-8fdc-9f29cf00b781",
                                "sense_id": "40a469c9-f541-3554-8119-608ebcf8558e",
                                "text": "The Skills Center, which is located on Amazon’s corporate headquarters campus in Seattle, Washington, and opens to the public November 22, is the first of its kind for the company. It’s part of a larger commitment to train 29 million people globally in cloud computing by 2025 that AWS made last year."
                            }
                        ]
                    }
                ],
                "translations": [],
                "word_linkages": []
            },
            {
                "entry_id": "d30f5f4e-7eae-3250-a9f2-32b691570e55",
                "word": "aws",
                "pos": "noun",
                "lang_code": "en",
                "forms": [],
                "senses": [
                    {
                        "sense_id": "bbeb58f6-8be8-36f4-862d-234eaf1e76ee",
                        "entry_id": "d30f5f4e-7eae-3250-a9f2-32b691570e55",
                        "glosses": [
                            "plural of aw"
                        ],
                        "tags": [
                            "form-of",
                            "plural"
                        ],
                        "examples": []
                    }
                ],
                "translations": [],
                "word_linkages": []
            },
            {
                "entry_id": "533dfde5-d017-3f53-931c-d09b6e85d574",
                "word": "AWS",
                "pos": "noun",
                "lang_code": "en",
                "forms": [],
                "senses": [
                    {
                        "sense_id": "106f5c7c-be90-383d-b486-fbb536abfe27",
                        "entry_id": "533dfde5-d017-3f53-931c-d09b6e85d574",
                        "glosses": [
                            "Initialism of advanced wireless services"
                        ],
                        "tags": [
                            "US",
                            "abbreviation",
                            "alt-of",
                            "initialism",
                            "plural",
                            "plural-only"
                        ],
                        "examples": []
                    }
                ],
                "translations": [],
                "word_linkages": []
            },
            {
                "entry_id": "b5a5cfa1-7fa5-3bef-82c1-c6362c9e93cc",
                "word": "AWS",
                "pos": "noun",
                "lang_code": "en",
                "forms": [
                    {
                        "form_id": "49f47f14-1f87-4560-b260-155e03dc5338",
                        "entry_id": "b5a5cfa1-7fa5-3bef-82c1-c6362c9e93cc",
                        "tags": [
                            "plural"
                        ],
                        "form": "AWSes"
                    }
                ],
                "senses": [
                    {
                        "sense_id": "3f5b4bc0-2131-3a5c-b103-e3367b118f8b",
                        "entry_id": "b5a5cfa1-7fa5-3bef-82c1-c6362c9e93cc",
                        "glosses": [
                            "Initialism of autonomous weapons system."
                        ],
                        "tags": [
                            "abbreviation",
                            "alt-of",
                            "initialism"
                        ],
                        "examples": [
                            {
                                "example_id": "7c1a421a-6aba-4e61-8172-74a1c5b916a7",
                                "sense_id": "3f5b4bc0-2131-3a5c-b103-e3367b118f8b",
                                "text": "“The concern that these weapons might misidentify targets is the least of our worries,” he said. “More significant is the threat of an A.W.S. arms race and proliferation crisis.”"
                            }
                        ]
                    },
                    {
                        "sense_id": "e86cd7c9-0d30-3d77-a845-42457e98a245",
                        "entry_id": "b5a5cfa1-7fa5-3bef-82c1-c6362c9e93cc",
                        "glosses": [
                            "Initialism of all-women shortlist."
                        ],
                        "tags": [
                            "UK",
                            "abbreviation",
                            "alt-of",
                            "initialism"
                        ],
                        "examples": []
                    }
                ],
                "translations": [],
                "word_linkages": []
            }
        ],
        "ru-extract.jsonl": [],
        "nl-extract.jsonl": [],
        "pl-extract.jsonl": [
            {
                "entry_id": "7d03f032-41c4-3b72-9992-250abfdbb5a4",
                "word": "AWS",
                "pos": "noun",
                "lang_code": "en",
                "forms": [],
                "senses": [
                    {
                        "sense_id": "71fb9152-36c6-3fbc-a62f-63cf59f05dbb",
                        "entry_id": "7d03f032-41c4-3b72-9992-250abfdbb5a4",
                        "glosses": [
                            "autonomous weapons systems → system uzbrojenia autonomicznego, autonomiczny system bojowy"
                        ],
                        "tags": [],
                        "examples": [],
                        "sense_index_json": "\"1.1\""
                    },
                    {
                        "sense_id": "cf5857e3-c481-3221-a85e-2bd09f91876c",
                        "entry_id": "7d03f032-41c4-3b72-9992-250abfdbb5a4",
                        "glosses": [
                            "automatic warning system → automatyczny system ostrzegania"
                        ],
                        "tags": [],
                        "examples": [],
                        "sense_index_json": "\"1.2\""
                    }
                ],
                "translations": [],
                "word_linkages": []
            }
        ],
        "fr-extract.jsonl": [],
        "it-extract.jsonl": [],
        "de-extract.jsonl": [],
        "cs-extract.jsonl": [],
        "es-extract.jsonl": [],
        "tr-extract.jsonl": [
            {
                "entry_id": "342f8cee-3eaa-3763-ae3b-3ba5b4adaa6f",
                "word": "AWS",
                "pos": "abbrev",
                "lang_code": "en",
                "forms": [],
                "senses": [
                    {
                        "sense_id": "c59f16c2-f00b-3c68-acba-f5c25dbe8689",
                        "entry_id": "342f8cee-3eaa-3763-ae3b-3ba5b4adaa6f",
                        "glosses": [
                            "Automatic Warning System kavramının kısaltması",
                            "(Otomatik İkaz Sistemi)"
                        ],
                        "tags": [
                            "abbreviation",
                            "form-of"
                        ],
                        "examples": []
                    },
                    {
                        "sense_id": "0b088c10-5c93-304d-b28c-7983827e2032",
                        "entry_id": "342f8cee-3eaa-3763-ae3b-3ba5b4adaa6f",
                        "glosses": [
                            "Automatic Warning System kavramının kısaltması",
                            "(Otomatik İkaz Sistemi)"
                        ],
                        "tags": [
                            "abbreviation",
                            "form-of"
                        ],
                        "examples": []
                    },
                    {
                        "sense_id": "63f81114-1646-3cd8-b044-8a1855e16962",
                        "entry_id": "342f8cee-3eaa-3763-ae3b-3ba5b4adaa6f",
                        "glosses": [
                            "Air Weather Service kavramının kısaltması",
                            "(Hava Meteoroloji Hizmeti)"
                        ],
                        "tags": [
                            "abbreviation",
                            "form-of"
                        ],
                        "examples": []
                    },
                    {
                        "sense_id": "e49d45ad-5303-3b23-8cc6-4585d5b3e501",
                        "entry_id": "342f8cee-3eaa-3763-ae3b-3ba5b4adaa6f",
                        "glosses": [
                            "Air Weather Service kavramının kısaltması",
                            "(Hava Meteoroloji Hizmeti)"
                        ],
                        "tags": [
                            "abbreviation",
                            "form-of"
                        ],
                        "examples": []
                    },
                    {
                        "sense_id": "05984222-632d-334e-bad2-1d5b1f9d6902",
                        "entry_id": "342f8cee-3eaa-3763-ae3b-3ba5b4adaa6f",
                        "glosses": [
                            "Amazon Web Services kavramının kısaltması",
                            "(Amazon'un Web Servisi)"
                        ],
                        "tags": [
                            "abbreviation",
                            "form-of"
                        ],
                        "examples": []
                    },
                    {
                        "sense_id": "d95a6b49-c3ab-380a-b226-ef427b836fa2",
                        "entry_id": "342f8cee-3eaa-3763-ae3b-3ba5b4adaa6f",
                        "glosses": [
                            "Amazon Web Services kavramının kısaltması",
                            "(Amazon'un Web Servisi)"
                        ],
                        "tags": [
                            "abbreviation",
                            "form-of"
                        ],
                        "examples": []
                    },
                    {
                        "sense_id": "6041d962-888a-3fa8-ab9b-09735add464e",
                        "entry_id": "342f8cee-3eaa-3763-ae3b-3ba5b4adaa6f",
                        "glosses": [
                            "American Welding Society kavramının kısaltması",
                            "(Amerikan Kaynak Cemiyeti)"
                        ],
                        "tags": [
                            "abbreviation",
                            "form-of"
                        ],
                        "examples": []
                    },
                    {
                        "sense_id": "a41e85aa-fa02-3ee7-8c61-41048fe068ea",
                        "entry_id": "342f8cee-3eaa-3763-ae3b-3ba5b4adaa6f",
                        "glosses": [
                            "American Welding Society kavramının kısaltması",
                            "(Amerikan Kaynak Cemiyeti)"
                        ],
                        "tags": [
                            "abbreviation",
                            "form-of"
                        ],
                        "examples": []
                    },
                    {
                        "sense_id": "4da98311-cc63-3ba3-a1d4-44a1d80a3d3a",
                        "entry_id": "342f8cee-3eaa-3763-ae3b-3ba5b4adaa6f",
                        "glosses": [
                            "Automatic Weather System kavramının kısaltması",
                            "(Otomatik Hava Durumu Sistemi)"
                        ],
                        "tags": [
                            "abbreviation",
                            "form-of"
                        ],
                        "examples": []
                    },
                    {
                        "sense_id": "9d5fef6b-d829-314c-9d35-6e5871f06c0d",
                        "entry_id": "342f8cee-3eaa-3763-ae3b-3ba5b4adaa6f",
                        "glosses": [
                            "Automatic Weather System kavramının kısaltması",
                            "(Otomatik Hava Durumu Sistemi)"
                        ],
                        "tags": [
                            "abbreviation",
                            "form-of"
                        ],
                        "examples": []
                    }
                ],
                "translations": [],
                "word_linkages": []
            }
        ]
    }
}