{
    "word": "catholical",
    "lang_code": "en",
    "source_file_to_entries": {
        "raw-wiktextract-data.jsonl": [
            {
                "entry_id": "e749decc-c9e9-361d-9bcf-a692ee7120d4",
                "word": "catholical",
                "pos": "adj",
                "lang_code": "en",
                "forms": [
                    {
                        "form_id": "65a362b7-6415-4315-bd3a-6feecbb4b579",
                        "entry_id": "e749decc-c9e9-361d-9bcf-a692ee7120d4",
                        "tags": [
                            "comparative"
                        ],
                        "form": "more catholical"
                    },
                    {
                        "form_id": "88ba2491-4acb-407e-8b8c-ad284e8f3632",
                        "entry_id": "e749decc-c9e9-361d-9bcf-a692ee7120d4",
                        "tags": [
                            "superlative"
                        ],
                        "form": "most catholical"
                    }
                ],
                "senses": [
                    {
                        "sense_id": "d26feb51-acce-351e-977d-017b5dd0a59b",
                        "entry_id": "e749decc-c9e9-361d-9bcf-a692ee7120d4",
                        "glosses": [
                            "Obsolete form of catholic."
                        ],
                        "tags": [
                            "alt-of",
                            "obsolete"
                        ],
                        "examples": []
                    }
                ],
                "translations": [],
                "word_linkages": []
            }
        ],
        "ru-extract.jsonl": [],
        "nl-extract.jsonl": [],
        "pl-extract.jsonl": [],
        "fr-extract.jsonl": [],
        "it-extract.jsonl": [],
        "de-extract.jsonl": [],
        "cs-extract.jsonl": [],
        "es-extract.jsonl": [],
        "tr-extract.jsonl": []
    }
}