{
    "word": "ottar",
    "lang_code": "en",
    "source_file_to_entries": {
        "raw-wiktextract-data.jsonl": [
            {
                "entry_id": "0405bc2b-bd7f-37cb-966d-d0e169c3c2a1",
                "word": "ottar",
                "pos": "noun",
                "lang_code": "en",
                "forms": [
                    {
                        "form_id": "41dd447e-d69d-4eb1-b564-02e99ebbff4b",
                        "entry_id": "0405bc2b-bd7f-37cb-966d-d0e169c3c2a1",
                        "tags": [
                            "plural"
                        ],
                        "form": "ottars"
                    }
                ],
                "senses": [
                    {
                        "sense_id": "569f6b17-5d54-33fb-9930-86322e7ed130",
                        "entry_id": "0405bc2b-bd7f-37cb-966d-d0e169c3c2a1",
                        "glosses": [
                            "Alternative form of attar."
                        ],
                        "tags": [
                            "alt-of",
                            "alternative",
                            "countable",
                            "uncountable"
                        ],
                        "examples": []
                    }
                ],
                "translations": [],
                "word_linkages": []
            }
        ],
        "ru-extract.jsonl": [],
        "nl-extract.jsonl": [],
        "pl-extract.jsonl": [],
        "fr-extract.jsonl": [],
        "it-extract.jsonl": [],
        "de-extract.jsonl": [],
        "cs-extract.jsonl": [],
        "es-extract.jsonl": [],
        "tr-extract.jsonl": []
    }
}