{
    "word": "poesie",
    "lang_code": "en",
    "source_file_to_entries": {
        "raw-wiktextract-data.jsonl": [
            {
                "entry_id": "8cdf20f9-5075-36f1-8413-2ee93e3f20f6",
                "word": "poesie",
                "pos": "noun",
                "lang_code": "en",
                "forms": [
                    {
                        "form_id": "e1a7a9dc-14de-42fe-a8d5-5d2e6ea24529",
                        "entry_id": "8cdf20f9-5075-36f1-8413-2ee93e3f20f6",
                        "tags": [
                            "plural"
                        ],
                        "form": "poesies"
                    }
                ],
                "senses": [
                    {
                        "sense_id": "0e390197-8f4e-3504-97de-94b67b61bb27",
                        "entry_id": "8cdf20f9-5075-36f1-8413-2ee93e3f20f6",
                        "glosses": [
                            "Alternative form of poesy."
                        ],
                        "tags": [
                            "alt-of",
                            "alternative",
                            "countable",
                            "literary",
                            "uncountable"
                        ],
                        "examples": []
                    }
                ],
                "translations": [],
                "word_linkages": []
            }
        ],
        "ru-extract.jsonl": [],
        "nl-extract.jsonl": [],
        "pl-extract.jsonl": [],
        "fr-extract.jsonl": [],
        "it-extract.jsonl": [],
        "de-extract.jsonl": [],
        "cs-extract.jsonl": [],
        "es-extract.jsonl": [],
        "tr-extract.jsonl": []
    }
}