{
    "word_family": [
        "śmierć",
        "śmiertelny",
        "umieralność",
        "wymierać",
        "obumierać",
        "zamierać",
        "przymierać"
    ],
    "entries": [
        {
            "pos": "verb",
            "senses": [
                {
                    "sense_id": "0d798d95-c2ed-31af-9890-66e500708430",
                    "sense_definition": "Przestawać żyć; kończyć swoje istnienie.",
                    "learner_level": "A1",
                    "frequency": "High",
                    "semantic_group_id": "death_process",
                    "name_type": "no",
                    "examples": [
                        {
                            "text": "Wszyscy ludzie rodzą się i w końcu <umierają>.",
                            "target_lang_translations": {
                                "ru": "Все люди рождаются и в конце концов <w>умирают</w>."
                            }
                        },
                        {
                            "text": "Pacjent <umierał> w szpitalu przez kilka dni.",
                            "target_lang_translations": {
                                "ru": "Пациент <w>умирал</w> в больнице несколько дней."
                            }
                        },
                        {
                            "text": "Nie chcę <umierać> w samotności z dala od rodziny.",
                            "target_lang_translations": {
                                "ru": "Я не хочу <w>умирать</w> в одиночестве вдали от семьи."
                            }
                        }
                    ],
                    "synonyms": [
                        "konać",
                        "odchodzić",
                        "gasnąć"
                    ],
                    "antonyms": [
                        "rodzić się",
                        "żyć"
                    ],
                    "common_phrases": [
                        "umierać ze śmiechu",
                        "umierać z nudów",
                        "umierać na raka",
                        "umierać młodo",
                        "bać się umierać"
                    ],
                    "target_lang_definitions": {
                        "ru": "Переставать жить; прекращать своё существование."
                    },
                    "translations": {
                        "ru": [
                            {
                                "target_lang_word": "умирать",
                                "target_lang_sense_clarification": "переставать жить"
                            }
                        ]
                    }
                }
            ]
        }
    ]
}