{
    "word_family": [
        "ślepnąć",
        "oślepnąć",
        "ślepota",
        "oślepiać",
        "ślepiec",
        "na ślepo"
    ],
    "entries": [
        {
            "pos": "adjective",
            "senses": [
                {
                    "sense_id": "8a042498-d0b7-3285-a52b-b148b32b6eb8",
                    "sense_definition": "Taki, który nie widzi lub stracił wzrok.",
                    "learner_level": "A2",
                    "frequency": "High",
                    "semantic_group_id": "physical_disability",
                    "name_type": "no",
                    "examples": [
                        {
                            "text": "Ten stary pies jest już prawie całkowicie <w>ślepy</w>."
                        },
                        {
                            "text": "Mój dziadek był <w>ślepy</w> na jedno oko po wypadku w pracy."
                        }
                    ],
                    "synonyms": [
                        "niewidomy",
                        "ociemniały"
                    ],
                    "antonyms": [
                        "widzący"
                    ],
                    "common_phrases": [
                        "ślepy na jedno oko",
                        "ślepy od urodzenia",
                        "całkowicie ślepy"
                    ]
                },
                {
                    "sense_id": "d1a08a26-9d8b-30b3-9d15-3e1ede81e35c",
                    "sense_definition": "O drodze, korytarzu lub pomieszczeniu: nieposiadający wylotu, zamknięty z jednej strony.",
                    "learner_level": "B2",
                    "frequency": "Middle",
                    "semantic_group_id": "spatial_dead_end",
                    "name_type": "no",
                    "examples": [
                        {
                            "text": "Kierowca zorientował się, że wjechał w <w>ślepą</w> uliczkę."
                        },
                        {
                            "text": "To śledztwo to <w>ślepy</w> zaułek, nie mamy żadnych nowych dowodów."
                        }
                    ],
                    "common_phrases": [
                        "ślepa uliczka",
                        "ślepy zaułek",
                        "ślepy tor"
                    ]
                },
                {
                    "sense_id": "1bcf5c3a-a5db-3d56-be1f-6bf9770e7dc1",
                    "sense_definition": "Taki, który nie dostrzega oczywistych faktów, prawdy lub czyichś wad.",
                    "learner_level": "B2",
                    "frequency": "Middle",
                    "semantic_group_id": "metaphorical_ignorance",
                    "name_type": "no",
                    "examples": [
                        {
                            "text": "Byłem <w>ślepy</w> i nie widziałem, że ona mnie okłamuje."
                        },
                        {
                            "text": "Politycy często są <w>ślepi</w> na codzienne problemy zwykłych obywateli."
                        }
                    ],
                    "synonyms": [
                        "zaślepiony"
                    ],
                    "common_phrases": [
                        "być ślepym na argumenty",
                        "być ślepym i głuchym"
                    ]
                },
                {
                    "sense_id": "8fbe506e-7a25-30d9-bb1e-02c92060d820",
                    "sense_definition": "Niekierujący się rozsądkiem, gwałtowny, bezkrytyczny lub przypadkowy.",
                    "learner_level": "C1",
                    "frequency": "Middle",
                    "semantic_group_id": "metaphorical_intensity",
                    "name_type": "no",
                    "examples": [
                        {
                            "text": "Żołnierz okazywał <w>ślepe</w> posłuszeństwo swojemu dowódcy."
                        },
                        {
                            "text": "O naszym zwycięstwie w tym meczu zadecydował <w>ślepy</w> traf."
                        }
                    ],
                    "synonyms": [
                        "zaślepiony"
                    ],
                    "common_phrases": [
                        "ślepy traf",
                        "ślepe posłuszeństwo",
                        "ślepa furia",
                        "ślepa miłość"
                    ]
                },
                {
                    "sense_id": "7411ae7c-5aef-3d58-8fd7-693f14fc8266",
                    "sense_definition": "W biologii: taki, który naturalnie nie posiada narządu wzroku.",
                    "learner_level": "C2",
                    "frequency": "Low",
                    "semantic_group_id": "biological_feature",
                    "name_type": "no",
                    "examples": [
                        {
                            "text": "W jaskiniach żyje specyficzny gatunek <w>ślepej</w> ryby."
                        },
                        {
                            "text": "Ewolucja sprawiła, że ten podziemny ssak jest całkowicie <w>ślepy</w>."
                        }
                    ]
                }
            ]
        },
        {
            "pos": "noun",
            "senses": [
                {
                    "sense_id": "8dbe7915-8f87-39f2-a537-0062e4fe2672",
                    "sense_definition": "Osoba, która nie widzi.",
                    "learner_level": "B1",
                    "frequency": "Middle",
                    "semantic_group_id": "person",
                    "name_type": "no",
                    "examples": [
                        {
                            "text": "Pomogłem temu <w>ślepemu</w> bezpiecznie przejść przez ruchliwą ulicę."
                        },
                        {
                            "text": "W dawnych czasach <w>ślepi</w> często zarabiali na życie graniem na instrumentach."
                        }
                    ],
                    "synonyms": [
                        "niewidomy",
                        "ślepiec"
                    ],
                    "traits": [
                        {
                            "trait_type": "colloquial",
                            "comment": "słowo 'niewidomy' jest bardziej uprzejme i formalne"
                        }
                    ]
                }
            ]
        }
    ]
}