{
    "word_family": [
        "оригинал",
        "оригинальный",
        "оригинально",
        "оригинальничать"
    ],
    "entries": [
        {
            "pos": "noun",
            "senses": [
                {
                    "sense_id": "cb371ded-b544-3f90-a9e3-8058f19d7ebf",
                    "sense_definition": "Свойство по значению прилагательного <w>оригинальный</w>; неповторимость, своеобразие.",
                    "learner_level": "B1",
                    "frequency": "Middle",
                    "semantic_group_id": "",
                    "name_type": "no",
                    "examples": [
                        {
                            "text": "Его работы всегда отличаются большой <w>оригинальностью</w>.",
                            "target_lang_translations": {
                                "en": "His works are always distinguished by great <w>originality</w>."
                            }
                        },
                        {
                            "text": "В этом решении нет никакой <w>оригинальности</w>.",
                            "target_lang_translations": {
                                "en": "There is no <w>originality</w> in this decision."
                            }
                        }
                    ],
                    "synonyms": [
                        "самобытность",
                        "своеобразие"
                    ],
                    "antonyms": [
                        "банальность",
                        "стандартность"
                    ],
                    "common_phrases": [
                        "отличаться оригинальностью",
                        "претендовать на оригинальность",
                        "проявить оригинальность"
                    ],
                    "target_lang_definitions": {
                        "en": "The quality of being original; uniqueness, distinctiveness."
                    },
                    "translations": {
                        "en": [
                            {
                                "target_lang_word": "originality",
                                "target_lang_sense_clarification": "the quality of being novel or unusual"
                            },
                            {
                                "target_lang_word": "uniqueness",
                                "target_lang_sense_clarification": "the quality of being the only one of its kind"
                            }
                        ]
                    }
                }
            ]
        }
    ]
}