{
    "word_family": [
        "отбор",
        "отбирать",
        "отобрать",
        "отборный"
    ],
    "entries": [
        {
            "pos": "adjective",
            "senses": [
                {
                    "sense_id": "7854487f-3a99-3395-94b8-52922f6dbae5",
                    "sense_definition": "Относящийся к предварительным состязаниям в спорте, по результатам которых определяются участники основных или финальных соревнований.",
                    "learner_level": "B1",
                    "frequency": "High",
                    "semantic_group_id": "",
                    "name_type": "no",
                    "examples": [
                        {
                            "text": "Наша команда выиграла решающий <w>отборочный</w> матч.",
                            "target_lang_translations": {
                                "en": "Our team won the decisive <w>qualifying</w> match."
                            }
                        },
                        {
                            "text": "В следующем месяце начнутся <w>отборочные</w> игры чемпионата мира.",
                            "target_lang_translations": {
                                "en": "The World Cup <w>qualifying</w> games will begin next month."
                            }
                        }
                    ],
                    "synonyms": [
                        "квалификационный"
                    ],
                    "antonyms": [
                        "финальный"
                    ],
                    "common_phrases": [
                        "отборочный матч",
                        "отборочный турнир",
                        "отборочный цикл",
                        "отборочная группа"
                    ],
                    "target_lang_definitions": {
                        "en": "Relating to preliminary sports competitions that determine the participants for the main or final events."
                    },
                    "translations": {
                        "en": [
                            {
                                "target_lang_word": "qualifying",
                                "target_lang_sense_clarification": "used to describe matches or rounds that determine who proceeds to the finals"
                            },
                            {
                                "target_lang_word": "preliminary",
                                "target_lang_sense_clarification": "occurring before the main part of a competition"
                            }
                        ]
                    }
                },
                {
                    "sense_id": "82490946-85cd-3c37-8fa2-04b9d14476a0",
                    "sense_definition": "Служащий для выбора, выделения кого-либо или чего-либо из общего числа по определённым признакам.",
                    "learner_level": "B2",
                    "frequency": "Middle",
                    "semantic_group_id": "",
                    "name_type": "no",
                    "examples": [
                        {
                            "text": "В университете начала работать <w>отборочная</w> комиссия для абитуриентов.",
                            "target_lang_translations": {
                                "en": "The <w>selection</w> committee for applicants has started working at the university."
                            }
                        },
                        {
                            "text": "Мы успешно прошли первый <w>отборочный</w> этап конкурса.",
                            "target_lang_translations": {
                                "en": "We successfully passed the first <w>selection</w> stage of the competition."
                            }
                        }
                    ],
                    "synonyms": [
                        "селекционный"
                    ],
                    "common_phrases": [
                        "отборочная комиссия",
                        "отборочный этап",
                        "отборочный тур"
                    ],
                    "target_lang_definitions": {
                        "en": "Serving to select or filter people or things from a larger group based on specific criteria."
                    },
                    "translations": {
                        "en": [
                            {
                                "target_lang_word": "selection",
                                "target_lang_sense_clarification": "relating to the process of choosing candidates or items (e.g., a committee)"
                            },
                            {
                                "target_lang_word": "screening",
                                "target_lang_sense_clarification": "intended to test or examine for suitability"
                            }
                        ]
                    }
                }
            ]
        }
    ]
}