{
    "word_family": [
        "язык",
        "языкознание",
        "языковед",
        "иноязычный",
        "русскоязычный",
        "двуязычный",
        "многоязычный",
        "межъязыковой"
    ],
    "entries": [
        {
            "pos": "adjective",
            "senses": [
                {
                    "sense_id": "f6738720-bc6c-3136-b682-8dbde995ada8",
                    "sense_definition": "Связанный с языком как средством общения, словесной речью и способами выражения мыслей.",
                    "learner_level": "B1",
                    "frequency": "High",
                    "semantic_group_id": "linguistics",
                    "name_type": "no",
                    "examples": [
                        {
                            "text": "Главной трудностью в путешествии для нас стал <w>языковой</w> барьер."
                        },
                        {
                            "text": "Для успешного обучения важно погрузиться в <w>языковую</w> среду."
                        }
                    ],
                    "synonyms": [
                        "лингвистический"
                    ],
                    "antonyms": [
                        "невербальный"
                    ],
                    "common_phrases": [
                        "языковой барьер",
                        "языковая среда",
                        "языковая семья",
                        "языковая норма",
                        "языковая практика"
                    ]
                }
            ]
        }
    ]
}